tox_timemachine/__init__.py
tox_timemachine/bisect.py
tox_timemachine/plugin.py
tox_timemachine-0.1.dist-info/LICENSE
tox_timemachine-0.1.dist-info/METADATA
tox_timemachine-0.1.dist-info/WHEEL
tox_timemachine-0.1.dist-info/entry_points.txt
tox_timemachine-0.1.dist-info/top_level.txt
tox_timemachine-0.1.dist-info/zip-safe
tox_timemachine-0.1.dist-info/RECORD
