Metadata-Version: 2.1
Name: tox-timemachine
Version: 0.1
Summary: Run tox on a date in the past
Home-page: https://github.com/astrofrog/tox-timemachine
Author: Thomas Robitaille
Author-email: thomas.robitaille@gmail.com
License: UNKNOWN
Platform: UNKNOWN
Requires-Dist: pypi-timemachine
Requires-Dist: setuptools
Requires-Dist: tox
